nicky/__init__.py
nicky/base.py
nicky/cli.py
nicky/commands/__init__.py
nicky/commands/cd_add.py
nicky/commands/cd_copy.py
nicky/commands/cd_name.py
nicky/commands/cd_sort.py
nicky/managers.py
nicky/nicknames/en/.gitkeep
nicky/nicknames/jp/.gitkeep
nicky/nicknames/ko/prefix.txt
nicky/nicknames/ko/suffix.txt
nicky/utils.py
nicky-2.0.0.dist-info/entry_points.txt
nicky-2.0.0.dist-info/LICENSE
nicky-2.0.0.dist-info/WHEEL
nicky-2.0.0.dist-info/METADATA
nicky-2.0.0.dist-info/RECORD
