Metadata-Version: 2.1
Name: nicky
Version: 2.0.0
Summary: Nicky the nicknamer
Home-page: https://github.com/jrog612/nicky
License: MIT
Author: jrog612
Author-email: jrog612@gmail.com
Requires-Python: >=3.6,<4.0
Classifier: License :: OSI Approved :: MIT License
Classifier: Programming Language :: Python :: 3
Classifier: Programming Language :: Python :: 3.6
Classifier: Programming Language :: Python :: 3.7
Classifier: Programming Language :: Python :: 3.8
Classifier: Programming Language :: Python :: 3.9
Requires-Dist: click (==7.0.0)
Project-URL: Repository, https://github.com/jrog612/nicky
